README.md
pyppeteerstealth/__init__.py
pyppeteerstealth-0.0.5.dist-info/METADATA
pyppeteerstealth-0.0.5.dist-info/WHEEL
pyppeteerstealth-0.0.5.dist-info/entry_points.txt
pyppeteerstealth-0.0.5.dist-info/RECORD
