Metadata-Version: 2.1
Name: pyppeteerstealth
Version: 0.0.5
Summary: A general collection of robot-evading tweaks for pyppeteer-ng
Home-page: https://github.com/dgtlmoon/pyppeteerstealth
License: MIT
Keywords: pyppeteer,puppeteer,chrome,chromium,pyppeteerstealth,stealth,robot,captcha
Classifier: Development Status :: 3 - Alpha
Classifier: Intended Audience :: Developers
Classifier: License :: OSI Approved :: MIT License
Classifier: Natural Language :: English
Classifier: Programming Language :: Python :: 2
Classifier: Programming Language :: Python :: 2.7
Classifier: Programming Language :: Python :: 3
Classifier: Programming Language :: Python :: 3.4
Classifier: Programming Language :: Python :: 3.5
Classifier: Programming Language :: Python :: 3.6
Classifier: Programming Language :: Python :: 3.7
Classifier: Programming Language :: Python :: 3.8
Classifier: Programming Language :: Python :: 3.9
Classifier: Programming Language :: Python :: 3.10
Classifier: Programming Language :: Python :: 3.11
Classifier: Programming Language :: Python :: 3.12
Project-URL: Bug Tracker, https://github.com/dgtlmoon/pyppeteerstealth/issues
Project-URL: Repository, https://github.com/dgtlmoon/pyppeteerstealth
